ctdfjorder/CTD.py
ctdfjorder/__init__.py
ctdfjorder/ai/__init__.py
ctdfjorder/ai/ai.py
ctdfjorder/cli/__init__.py
ctdfjorder/cli/cli.py
ctdfjorder/constants/__init__.py
ctdfjorder/constants/constants.py
ctdfjorder/dataclasses/__init__.py
ctdfjorder/dataclasses/dataclasses.py
ctdfjorder/exceptions/__init__.py
ctdfjorder/exceptions/exceptions.py
ctdfjorder/loadctd/__init__.py
ctdfjorder/loadctd/aml.py
ctdfjorder/loadctd/castaway.py
ctdfjorder/loadctd/rsk.py
ctdfjorder/metadata/__init__.py
ctdfjorder/metadata/master_sheet.py
ctdfjorder/pyrsktools/LICENSE.txt
ctdfjorder/pyrsktools/__init__.py
ctdfjorder/pyrsktools/channel_types.py
ctdfjorder/utils/__init__.py
ctdfjorder/utils/utils.py
ctdfjorder/visualize/__init__.py
ctdfjorder/visualize/ctd_plot.py
ctdfjorder-0.8.91.dist-info/LICENSE.txt
ctdfjorder-0.8.91.dist-info/METADATA
ctdfjorder-0.8.91.dist-info/WHEEL
ctdfjorder-0.8.91.dist-info/entry_points.txt
ctdfjorder-0.8.91.dist-info/RECORD
