Metadata-Version: 2.1
Name: ctdfjorder
Version: 0.8.91
Summary: A package for processing and analyzing CTD data.
Home-page: https://github.com/nikothomas/ctdfjorder
License: MIT
Keywords: CTD,Oceanography,Python,RBR,Castaway
Author: Nikolas Yanek-Chrones
Author-email: research@icarai.io
Requires-Python: >=3.11,<4.0
Classifier: Development Status :: 4 - Beta
Classifier: License :: OSI Approved :: MIT License
Classifier: Operating System :: OS Independent
Classifier: Programming Language :: Python :: 3
Classifier: Programming Language :: Python :: 3.11
Classifier: Programming Language :: Python :: 3.12
Requires-Dist: dash (>=2.17.1,<3.0.0)
Requires-Dist: fastexcel (>=0.10.4)
Requires-Dist: flask (>=3.0.3,<4.0.0)
Requires-Dist: gsw (>=3.6.18)
Requires-Dist: matplotlib (>=3.9.2)
Requires-Dist: numpy (>=2.1.0)
Requires-Dist: plotly (>=5.20.0,<6.0.0)
Requires-Dist: polars (>=1.5.0)
Requires-Dist: psutil (>=6.0.0,<7.0.0)
Requires-Dist: pyarrow (>=17.0.0)
Requires-Dist: rich (>=13.7.1,<14.0.0)
Requires-Dist: rich-argparse (>=1.5.2,<2.0.0)
Requires-Dist: scikit-learn (>=1.5.1,<2.0.0)
Requires-Dist: statsmodels (>=0.14.2)
Requires-Dist: torch (>=2.4.0) ; sys_platform != "darwin"
Requires-Dist: torch (>=2.4.0) ; sys_platform == "darwin"
Project-URL: Documentation, https://ctdfjorder.readthedocs.io
Project-URL: Repository, https://github.com/nikothomas/ctdfjorder
Project-URL: homepage, https://github.com/nikothomas/ctdfjorder
Project-URL: issues, https://github.com/nikothomas/ctdfjorder/issues
